nimble_py/__init__.py
nimble_py/aws_utils.py
nimble_py/common
nimble_py/common_utils.py
nimble_py/file_utils.py
nimble_py/log_util.py
nimble_py/pandas_utils.py
nimble_py/py_utils.py
nimble_py-0.0.1.dist-info/METADATA
nimble_py-0.0.1.dist-info/WHEEL
nimble_py-0.0.1.dist-info/licenses/LICENSE
nimble_py-0.0.1.dist-info/RECORD
