Metadata-Version: 2.1
Name: nimble-py
Version: 0.0.1
Summary: A collection of simple but powerful utilities for Data Analytics and Data Science workflows.
Project-URL: Homepage, https://github.com/sarfarazm/nimble-py
Project-URL: Bug Tracker, https://github.com/sarfarazm/nimble-py/issues
Author-email: Sarfaraz Memon <memon.sarfaraz@gmail.com>
License-File: LICENSE
Classifier: License :: OSI Approved :: MIT License
Classifier: Operating System :: OS Independent
Classifier: Programming Language :: Python :: 3
Requires-Python: >=3.8
Requires-Dist: gspread>=5.4.0
Requires-Dist: mysql-connector>=2.2.9
Requires-Dist: numpy>=1.21.0
Requires-Dist: oauth2client>=4.1.3
Requires-Dist: openpyxl>=3.0.0
Requires-Dist: pandas>=1.3.1
Requires-Dist: psycopg2-binary>=2.8.5
Requires-Dist: pymongo>=3.10.1
Requires-Dist: pyyaml>=5.4.1
Requires-Dist: requests>=2.25.21
Requires-Dist: s3fs==0.4.2
Requires-Dist: xlsxwriter>=1.3.7
